imarkdown_notebooks/.gitignore
imarkdown_notebooks/.travis.yml
imarkdown_notebooks/CONTRIBUTING.md
imarkdown_notebooks/README.md
imarkdown_notebooks/__init__.py
imarkdown_notebooks/_version.py
imarkdown_notebooks/config.py
imarkdown_notebooks/extension.py
imarkdown_notebooks/handlers.py
imarkdown_notebooks/imarkdownapp.py
imarkdown_notebooks/index.html
imarkdown_notebooks/package-2.json
imarkdown_notebooks/package-lock.json
imarkdown_notebooks/package.json
imarkdown_notebooks/python_language_server.py
imarkdown_notebooks/test.md
imarkdown_notebooks/testd.md
imarkdown_notebooks/webpack-old.config.js
imarkdown_notebooks/webpack.config.js
imarkdown_notebooks/dist/0.bundle.js
imarkdown_notebooks/dist/0.bundle.js.map
imarkdown_notebooks/dist/0.js
imarkdown_notebooks/dist/1.bundle.js
imarkdown_notebooks/dist/1.bundle.js.map
imarkdown_notebooks/dist/1.js
imarkdown_notebooks/dist/10.bundle.js
imarkdown_notebooks/dist/10.bundle.js.map
imarkdown_notebooks/dist/10.js
imarkdown_notebooks/dist/100.bundle.js
imarkdown_notebooks/dist/100.bundle.js.map
imarkdown_notebooks/dist/101.bundle.js
imarkdown_notebooks/dist/101.bundle.js.map
imarkdown_notebooks/dist/102.bundle.js
imarkdown_notebooks/dist/102.bundle.js.map
imarkdown_notebooks/dist/103.bundle.js
imarkdown_notebooks/dist/103.bundle.js.map
imarkdown_notebooks/dist/104.bundle.js
imarkdown_notebooks/dist/104.bundle.js.map
imarkdown_notebooks/dist/105.bundle.js
imarkdown_notebooks/dist/105.bundle.js.map
imarkdown_notebooks/dist/106.bundle.js
imarkdown_notebooks/dist/106.bundle.js.map
imarkdown_notebooks/dist/107.bundle.js
imarkdown_notebooks/dist/107.bundle.js.map
imarkdown_notebooks/dist/108.bundle.js
imarkdown_notebooks/dist/108.bundle.js.map
imarkdown_notebooks/dist/109.bundle.js
imarkdown_notebooks/dist/109.bundle.js.map
imarkdown_notebooks/dist/11.bundle.js
imarkdown_notebooks/dist/11.bundle.js.map
imarkdown_notebooks/dist/11.js
imarkdown_notebooks/dist/110.bundle.js
imarkdown_notebooks/dist/110.bundle.js.map
imarkdown_notebooks-0.0.2.dist-info/METADATA
imarkdown_notebooks-0.0.2.dist-info/WHEEL
imarkdown_notebooks-0.0.2.dist-info/entry_points.txt
imarkdown_notebooks-0.0.2.dist-info/top_level.txt
imarkdown_notebooks-0.0.2.dist-info/RECORD
