Metadata-Version: 2.1
Name: imarkdown-notebooks
Version: 0.0.2
Summary: Extension for the jupyter notebook server and nteract
Home-page: https://github.com/nteract/nteract
Author: nteract contributors
Author-email: jupyter@googlegroups.com
License: UNKNOWN
Platform: UNKNOWN
Requires-Dist: notebook
Requires-Dist: python-jsonrpc-server
Requires-Dist: python-language-server
